dense_ev/__init__.py
dense_ev/decompose_pauli.py
dense_ev/dense_grouper.py
dense_ev/dense_pauli_basis_change.py
dense_ev/dense_pauli_expectation.py
dense_ev/rmatrix.py
dense_ev/test_ops.py
dense_ev-2023.5.22.dist-info/LICENSE.txt
dense_ev-2023.5.22.dist-info/METADATA
dense_ev-2023.5.22.dist-info/WHEEL
dense_ev-2023.5.22.dist-info/top_level.txt
dense_ev-2023.5.22.dist-info/RECORD
