Metadata-Version: 2.1
Name: dense-ev
Version: 2023.5.22
Summary: Qiskit expectation values using optimal dense grouping.
Author-email: Andrew Lytle <atlytle@illinois.edu>
License: Apache License
Project-URL: Homepage, https://github.com/atlytle/dense-ev
License-File: LICENSE.txt
Requires-Dist: qiskit (<0.43.0)
Requires-Dist: psfam
